{
  "date": "2026-05-23T04:38:01.556Z",
  "stories": [
    {
      "id": "2026-05-23-01",
      "category": "geopolitique",
      "title": "Les États-Unis sanctionnent un haut policier tanzanien",
      "imageUrl": "https://s.rfi.fr/media/display/a033ac70-9051-11ef-a4dd-005056bf30b7/w:1024/p:16x9/2024-10-20T140047Z_1576146266_RC296AAQMCD6_RTRMADP_3_TANZANIA-POLITICS.JPG",
      "location": {
        "lat": -6.7924,
        "lng": 39.2083,
        "name": "Dar es Salaam, Tanzanie"
      },
      "bullets": [
        "Les États-Unis sanctionnent le policier tanzanien Faustine Jackson Mafwele",
        "Des accusations de torture et de violences sexuelles contre deux militants",
        "Les deux militants est-africains avaient été arrêtés à Dar es Salaam en 2025",
        "La Tanzanie n'a pas réagi publiquement à ces sanctions américaines",
        "Un signal de Washington sur les droits humains en Afrique de l'Est"
      ],
      "execSummary": "Le 21 mai, le département d'État américain a imposé des sanctions contre Faustine Jackson Mafwele, un haut responsable de la police tanzanienne. Selon RFI, ce dernier est accusé d'être impliqué dans de graves violations des droits humains, notamment des actes de torture et des violences sexuelles, commis contre deux militants est-africains arrêtés il y a environ un an à Dar es Salaam, la capitale économique de la Tanzanie.\n\nDu côté américain, cette décision s'inscrit dans le cadre de la politique de sanctions individuelles ciblant les responsables étrangers impliqués dans des atteintes aux droits fondamentaux. Washington utilise régulièrement ce levier, fondé notamment sur le Global Magnitsky Act, pour signaler que certains abus ne resteront pas sans conséquences, même lorsqu'ils sont commis par des agents d'États partenaires. Les sanctions gèlent les éventuels avoirs du policier aux États-Unis et lui interdisent l'entrée sur le territoire américain.\n\nDu côté tanzanien, aucune réaction officielle n'a été relayée par les sources disponibles. Historiquement, Dar es Salaam tend à considérer ce type de mesures unilatérales comme une ingérence dans ses affaires intérieures. Les organisations de défense des droits humains, elles, dénoncent depuis plusieurs années un rétrécissement de l'espace civique en Tanzanie, où militants et opposants font régulièrement l'objet d'arrestations et de détentions arbitraires.\n\nCette affaire illustre les tensions récurrentes entre diplomatie américaine et souveraineté des États africains en matière de droits humains. Pour la Tanzanie, qui cherche à attirer les investissements étrangers et à consolider ses relations internationales, ces sanctions constituent un signal négatif. Plus largement, elles posent la question de l'efficacité réelle de telles mesures individuelles face à des pratiques systémiques, alors que Washington doit lui-même gérer ses propres controverses internes, comme le montrent d'autres actualités américaines de la même semaine.",
      "sources": [
        "RFI",
        "Le Monde - International",
        "France 24"
      ],
      "publishedAt": "2026-05-23T04:21:17.000Z"
    },
    {
      "id": "2026-05-23-02",
      "category": "geopolitique",
      "title": "La Russie promet des représailles après une frappe sur un lycée",
      "imageUrl": "https://s.rfi.fr/media/display/7f6a613e-55f6-11f1-8369-005056bfb2b6/w:1024/p:16x9/AP26142371631181.jpg",
      "location": {
        "lat": 48.57,
        "lng": 39.31,
        "name": "Région de Louhansk, Ukraine"
      },
      "bullets": [
        "Une frappe de drones ukrainiens touche un lycée en zone occupée par la Russie",
        "Le bilan fait au moins six morts, des dizaines de blessés et quinze disparus",
        "La Russie dénonce un « crime monstrueux » et Vladimir Poutine promet des représailles",
        "L'Ukraine affirme avoir visé une unité militaire d'élite, pas des civils",
        "L'escalade complique les perspectives de négociations entre les deux pays"
      ],
      "execSummary": "Le 22 mai 2026, une frappe de drones ukrainiens a touché un bâtiment décrit par les autorités russes comme un lycée (ou « college ») dans la région de Louhansk, territoire ukrainien occupé par la Russie depuis 2022. Selon RFI et la BBC, le bilan s'élève à au moins six morts, des dizaines de blessés et quinze personnes portées disparues. Vladimir Poutine a réagi en promettant des représailles contre l'Ukraine. Parallèlement, Le Monde rapporte que Volodymyr Zelensky a revendiqué la reprise de 590 kilomètres carrés de territoire et la poursuite de frappes à longue portée contre les infrastructures énergétiques russes, notamment une raffinerie à Iaroslavl, à 700 kilomètres de la frontière.\n\nDu côté russe, les autorités ont qualifié cette frappe de « crime monstrueux » visant délibérément des civils, en l'occurrence un établissement scolaire. Vladimir Poutine a utilisé cet événement pour justifier de futures représailles militaires, inscrivant cet épisode dans le récit d'une Ukraine qui ciblerait volontairement des populations civiles dans les territoires que Moscou considère comme faisant partie de la Russie.\n\nDu côté ukrainien, l'armée a contesté la version russe. Selon la BBC, Kiev affirme avoir visé l'unité militaire d'élite Rubicon, spécialisée dans les drones, stationnée dans cette partie occupée de l'est de l'Ukraine. L'armée ukrainienne dément avoir ciblé des civils, laissant entendre que la présence militaire russe à proximité ou dans des infrastructures civiles est en cause. Le Monde souligne par ailleurs que Zelensky considère que « la tendance n'est clairement pas en faveur » de Moscou sur le plan militaire.\n\nCet incident illustre l'escalade continue du conflit et la difficulté croissante à distinguer cibles militaires et civiles dans les zones occupées. Les représailles promises par Poutine pourraient entraîner une intensification des bombardements sur le territoire ukrainien. Alors que les deux parties revendiquent des avancées sur le terrain, cet épisode éloigne encore les perspectives de cessez-le-feu, chaque camp instrumentalisant les pertes civiles pour justifier la poursuite des hostilités.",
      "sources": [
        "BBC World",
        "Le Monde - International",
        "RFI"
      ],
      "publishedAt": "2026-05-23T04:05:03.000Z"
    },
    {
      "id": "2026-05-23-03",
      "category": "geopolitique",
      "title": "L'UE et le Mexique signent un accord commercial majeur",
      "imageUrl": "https://focus.courrierinternational.com/2026/05/22/0/0/3423/2282/1200/630/60/0/589a379_ftp-1-l2ru0s49kscs-afp-b3t666c.jpg",
      "location": {
        "lat": 19.4326,
        "lng": -99.1332,
        "name": "Mexico, Mexique"
      },
      "bullets": [
        "L'Union européenne et le Mexique signent un accord réduisant leurs droits de douane",
        "Le contexte des guerres commerciales lancées par les États-Unis accélère ce rapprochement",
        "L'accord couvre les produits agroalimentaires et les pièces automobiles",
        "Les deux blocs cherchent à diversifier leurs partenariats face au protectionnisme américain",
        "Un enjeu stratégique de repositionnement dans le commerce mondial"
      ],
      "execSummary": "L'Union européenne et le Mexique ont signé un accord commercial visant à réduire mutuellement leurs droits de douane. L'accord, conclu entre la présidente mexicaine Claudia Sheinbaum et la présidente de la Commission européenne Ursula von der Leyen, porte sur de nombreux produits agroalimentaires et facilite également le commerce des pièces automobiles. Selon Le Monde, il s'agit d'un texte de grande ampleur couvrant plusieurs secteurs stratégiques.\n\nDu côté européen, cet accord s'inscrit dans une stratégie de diversification des partenariats commerciaux. Face à la montée du protectionnisme américain et aux droits de douane imposés par Washington, Bruxelles cherche à multiplier les accords bilatéraux pour sécuriser ses chaînes d'approvisionnement et maintenir ses débouchés à l'exportation. L'UE présente ce texte comme un signal fort en faveur du libre-échange.\n\nPour le Mexique, l'enjeu est similaire : réduire sa dépendance commerciale vis-à-vis des États-Unis, son premier partenaire. Comme le souligne Courrier International, qui replace cette signature dans un panorama d'actualités internationales incluant aussi le Sénégal et la politique américaine, le Mexique traverse une période de tensions avec Washington sur les questions douanières. Cet accord avec l'UE offre à Mexico un levier de négociation et une alternative économique crédible.\n\nLes conséquences de cet accord pourraient être significatives pour le commerce transatlantique. En facilitant les échanges de pièces automobiles, il pourrait reconfigurer une partie des chaînes de production dans le secteur automobile mondial. Plus largement, cette signature illustre un mouvement de fond : face au repli protectionniste américain, d'autres puissances accélèrent leurs alliances commerciales. La question reste de savoir si ces accords bilatéraux suffiront à compenser les perturbations causées par les politiques tarifaires de Washington.",
      "sources": [
        "Courrier International",
        "Le Monde - International"
      ],
      "publishedAt": "2026-05-23T03:56:15.000Z"
    },
    {
      "id": "2026-05-23-04",
      "category": "geopolitique",
      "title": "Sénégal : le président Faye limoge le Premier ministre Sonko",
      "imageUrl": "https://s.france24.com/media/display/ec104278-563b-11f1-8432-005056a97e36/w:1024/p:16x9/vignette-sonko-3.jpg",
      "location": {
        "lat": 14.6928,
        "lng": -17.4467,
        "name": "Dakar, Sénégal"
      },
      "bullets": [
        "Le président Bassirou Diomaye Faye a limogé Ousmane Sonko par décret vendredi soir.",
        "Des mois de tensions croissantes entre les deux anciens alliés ont précédé la rupture.",
        "Le décret met également fin aux fonctions de l'ensemble du gouvernement.",
        "Les deux hommes étaient arrivés au pouvoir ensemble en avril 2024 portés par l'espoir populaire.",
        "L'avenir politique du Sénégal s'annonce incertain après cette rupture majeure."
      ],
      "execSummary": "Le président sénégalais Bassirou Diomaye Faye a mis fin aux fonctions de son Premier ministre Ousmane Sonko et de l'ensemble de son gouvernement par décret, dans la soirée du vendredi 22 mai 2026. L'annonce a été diffusée par la chaîne de télévision publique RTS peu avant 22 heures, heure universelle. Ce limogeage marque la rupture définitive entre les deux figures politiques qui avaient accédé ensemble au pouvoir.\n\nCette décision intervient après des mois de tensions croissantes entre le président et son ancien mentor. Arrivés au pouvoir en avril 2024 à la faveur d'un immense espoir populaire de changement, Bassirou Diomaye Faye et Ousmane Sonko incarnaient une nouvelle génération politique au Sénégal. Sonko, figure charismatique de l'opposition devenue chef du gouvernement, a progressivement vu ses relations se dégrader avec le président qu'il avait contribué à faire élire, jusqu'à une rupture devenue irréversible.\n\nL'information, rapportée simultanément par Le Monde, France 24 et RFI, confirme l'ampleur de l'événement politique. France 24, s'appuyant sur son correspondant à Dakar Elimane Ndao, souligne que Sonko a été « remercié » par le président. RFI précise que la décision a été prise de manière unilatérale par le chef de l'État. Le Monde qualifie Sonko d'« ancien mentor » de Faye, rappelant ainsi l'inversion du rapport de force entre les deux hommes depuis leur accession au pouvoir.\n\nCe bouleversement politique ouvre une période d'incertitude majeure pour le Sénégal. La nomination d'un nouveau Premier ministre et la formation d'un nouveau gouvernement seront scrutées de près, tant par la classe politique sénégalaise que par les partenaires internationaux du pays. La question de la réaction des partisans de Sonko, dont la popularité reste forte, constitue un enjeu central pour la stabilité du pays dans les semaines à venir.",
      "sources": [
        "Le Monde",
        "France 24",
        "RFI"
      ],
      "publishedAt": "2026-05-23T04:21:17.000Z"
    },
    {
      "id": "2026-05-23-05",
      "category": "tech",
      "title": "Waymo suspend la conduite sur autoroute après des incidents",
      "imageUrl": "https://platform.theverge.com/wp-content/uploads/sites/2/2025/11/SF_WAYMO-FREEWAY_FRONT.jpg?quality=90&#038;strip=all&#038;crop=0,0,100,100",
      "location": {
        "lat": 29.4241,
        "lng": -98.4936,
        "name": "San Antonio, Texas"
      },
      "bullets": [
        "La société Waymo a suspendu la conduite sur autoroute dans tous ses marchés américains.",
        "Des robotaxis ont été filmés roulant à grande vitesse sur des routes inondées au Texas.",
        "L'entreprise a émis un rappel logiciel pour l'ensemble de sa flotte de véhicules autonomes.",
        "Les services à Atlanta et San Antonio ont été entièrement suspendus temporairement.",
        "La fiabilité des véhicules autonomes face aux conditions réelles est remise en question."
      ],
      "execSummary": "Waymo a annoncé la suspension de la conduite sur autoroute pour l'ensemble de ses robotaxis aux États-Unis, après la découverte de problèmes liés aux zones de travaux. Les clients ont constaté jeudi que le service autoroutier n'était plus disponible dans l'application, leurs trajets étant redirigés vers des routes locales avec des temps de parcours considérablement allongés. Les services ont également été entièrement suspendus à Atlanta et San Antonio en raison de routes inondées.\n\nCette décision intervient dans un contexte particulièrement délicat pour l'entreprise de conduite autonome. Plusieurs de ses véhicules ont été filmés circulant à grande vitesse sur des routes inondées au Texas, forçant Waymo à procéder à un rappel logiciel concernant l'intégralité de sa flotte. Ces incidents soulèvent des questions fondamentales sur la capacité des systèmes autonomes à gérer des conditions routières inhabituelles, qu'il s'agisse d'intempéries ou de configurations modifiées par des travaux.\n\nWaymo a confirmé la suspension et reconnu les problèmes identifiés, procédant rapidement au rappel de ses logiciels. Selon The Verge, l'entreprise travaille à corriger les lacunes de ses systèmes face aux zones de construction et aux conditions météorologiques dégradées. Les utilisateurs, eux, ont exprimé leur frustration face à l'allongement soudain des temps de trajet.\n\nCet épisode constitue un revers significatif pour le secteur des véhicules autonomes, qui cherche à démontrer sa fiabilité pour obtenir des autorisations d'exploitation élargies. La capacité de Waymo à rétablir rapidement et en toute sécurité ses services autoroutiers sera scrutée de près par les régulateurs et le public, alors que l'entreprise est considérée comme le leader du marché de la conduite autonome commerciale aux États-Unis.",
      "sources": [
        "The Verge"
      ],
      "publishedAt": "2026-05-23T04:00:44.000Z"
    },
    {
      "id": "2026-05-23-06",
      "category": "eco",
      "title": "Crise énergétique : le blocage d'Ormuz menace l'été",
      "imageUrl": "https://images.unsplash.com/photo-1451187580459-43490279c0fa?w=800",
      "location": {
        "lat": 26.5,
        "lng": 56.25,
        "name": "Détroit d'Ormuz"
      },
      "bullets": [
        "La diminution rapide des stocks pétroliers fait craindre des pénuries estivales",
        "Le blocage du détroit d'Ormuz par l'Iran provoque des tensions majeures",
        "L'Iran envisage de taxer les câbles télécoms sous-marins du détroit",
        "Les compagnies aériennes comme EasyJet surveillent les approvisionnements en kérosène",
        "Les prix des carburants pèsent sur les consommateurs et les entreprises mondiales"
      ],
      "execSummary": "Le blocage du détroit d'Ormuz par l'Iran provoque une diminution rapide des stocks mondiaux de pétrole, faisant craindre des tensions accrues sur les produits raffinés, notamment le kérosène, à l'approche de la saison estivale. Selon Le Monde, la situation fait redouter un été de tous les dangers sur le marché mondial de l'énergie. Parallèlement, Téhéran envisage d'étendre son contrôle du goulet maritime en taxant les utilisateurs des câbles télécoms sous-marins qui y transitent, des infrastructures vitales pour Internet et des secteurs sensibles comme l'énergie et la banque.\n\nCette crise énergétique a des répercussions mondiales en cascade. En France, la flambée des prix des carburants a conduit la Commission européenne à valider des aides de l'État français aux pêcheurs, tandis que la CGT plaide pour un blocage des prix. Aux États-Unis, Walmart avertit que ses clients réduisent leurs dépenses en raison de la hausse des prix à la pompe, selon la BBC. Le contexte pèse également sur l'économie française, dont les perspectives de croissance sont revues à la baisse par le FMI et la Commission européenne.\n\nLes réactions des acteurs économiques varient. Le patron d'EasyJet assure, selon la BBC, que les vols d'été ne seront pas affectés par les pénuries de kérosène, tout en reconnaissant que l'incertitude liée à la guerre en Iran pousse les voyageurs à réserver plus tardivement. En France, les syndicats réclament des mesures fortes, la CGT demandant un gel des prix des carburants, tandis que le gouvernement multiplie les dispositifs d'aide ciblés.\n\nLes enjeux sont considérables pour l'économie mondiale. La prolongation du blocage d'Ormuz pourrait aggraver les pénuries de carburant pendant la haute saison touristique, avec des conséquences sur le transport aérien, le commerce maritime et le pouvoir d'achat des ménages. La menace iranienne sur les câbles sous-marins ajoute une dimension supplémentaire au risque, menaçant les infrastructures numériques mondiales et la stabilité des marchés financiers.",
      "sources": [
        "Le Monde - Économie",
        "BBC Business"
      ],
      "publishedAt": "2026-05-23T04:00:39.000Z"
    }
  ]
}