{
  "generatedAt": "2026-05-28T05:06:59.361Z",
  "clusterCount": 5,
  "clusters": [
    {
      "id": "cluster-3",
      "topic": "Nouvelles frappes américaines en Iran, Téhéran réplique en visant une base améri",
      "category": "geopolitique",
      "importance": 10,
      "articles": [
        {
          "id": "2026-05-28-a099c625",
          "title": "Nouvelles frappes américaines en Iran, Téhéran réplique en visant une base américaine",
          "description": "Les affrontements survenus dans la nuit de mercredi à jeudi sont les plus graves depuis le début du cessez-le-feu le 8 avril. Les bombardements et les combats se poursuivent au Liban, malgré la trêve entrée en vigueur le 17 avril.",
          "url": "https://www.lemonde.fr/international/article/2026/05/28/nouvelles-frappes-americaines-en-iran-teheran-replique-en-visant-une-base-americaine_6694423_3210.html",
          "imageUrl": null,
          "source": "Le Monde - International",
          "category": "geopolitique",
          "publishedAt": "2026-05-28T04:49:14.000Z",
          "fetchedAt": "2026-05-28T05:02:58.764Z"
        },
        {
          "id": "2026-05-28-5c61f81e",
          "title": "EN DIRECT - Guerre au Moyen-Orient: les États-Unis frappent l'Iran qui réplique en visant une base américaine",
          "description": "L'armée américaine a mené de nouvelles frappes dans le ⁠sud de l'Iran, ​a dit un responsable américain. Les Gardiens de la Révolution iraniens ont annoncé jeudi 28 mai avoir visé une base américaine, sans préciser laquelle. Ces affrontements sont les plus graves depuis le début du cessez-le-feu. De son côté, le président américain, Donald Trump a démenti mercredi 27 mai des informations iraniennes sur un projet d'accord conférant à Téhéran la gestion du détroit d'Ormuz.",
          "url": "https://www.rfi.fr/fr/moyen-orient/20260528-en-direct-guerre-au-moyen-orient-les-%C3%A9tats-unis-frappent-l-iran-qui-r%C3%A9plique-en-visant-une-base-am%C3%A9ricaine",
          "imageUrl": "https://s.rfi.fr/media/display/34d4a99c-5a4a-11f1-923e-005056a90284/w:1024/p:16x9/063-2278473886.jpg",
          "source": "RFI",
          "category": "geopolitique",
          "publishedAt": "2026-05-28T04:12:31.000Z",
          "fetchedAt": "2026-05-28T05:03:08.707Z"
        },
        {
          "id": "2026-05-28-afcd69c9",
          "title": "EN DIRECT, guerre au Moyen-Orient : l’Iran dit avoir visé des bases américaines en représailles à des frappes menées plus tôt dans le sud du pays",
          "description": "L’armée du Koweït a annoncé être en train de repousser « des attaques de missiles et drones ennemis », alors que, selon un responsable américain, les Etats-Unis ont abattu, au cours de la nuit, quatre drones iraniens et mené des frappes sur une base au sol dans le sud de l’Iran, lors d’actions « défensives ».",
          "url": "https://www.lemonde.fr/international/live/2026/05/28/en-direct-guerre-au-moyen-orient-l-iran-dit-avoir-vise-des-bases-americaines-en-represailles-a-des-frappes-menees-plus-tot-dans-le-sud-du-pays_6694380_3210.html",
          "imageUrl": null,
          "source": "Le Monde - International",
          "category": "geopolitique",
          "publishedAt": "2026-05-28T03:45:49.000Z",
          "fetchedAt": "2026-05-28T05:02:58.764Z"
        },
        {
          "id": "2026-05-28-85a9659f",
          "title": "Iran en direct : les Gardiens de la Révolution visent une base américaine en représailles à des frappes",
          "description": "",
          "url": "https://www.france24.com/fr/moyen-orient/20260528-en-direct-moyen-orient-iran-etats-unis-nouvelles-frappes-israel-liban-donald-trump",
          "imageUrl": "https://s.france24.com/media/display/10976ee0-47f1-11f1-875c-005056bf30b7/w:1280/p:16x9/AP26124411625144.jpg",
          "source": "France 24",
          "category": "geopolitique",
          "publishedAt": "2026-05-28T03:35:53.000Z",
          "fetchedAt": "2026-05-28T05:02:58.810Z"
        },
        {
          "id": "2026-05-28-17e1ac87",
          "title": "Guerre au Moyen-Orient : les Etats-Unis disent avoir mené des frappes « défensives » dans le sud de l’Iran. Retrouvez les informations du 21 au 27 mai.",
          "description": "Quatre drones d’attaque qui représentaient une « menace autour du détroit d’Ormuz » ont été abattus, a déclaré un responsable américain sous le couvert de l’anonymat. L’armée américaine a aussi frappé « une station de contrôle au sol à Bandar-e Abbas, qui menaçait de lancer un cinquième drone ».",
          "url": "https://www.lemonde.fr/international/live/2026/05/28/en-direct-guerre-au-moyen-orient-les-medias-iraniens-font-etat-de-trois-fortes-explosions-nocturnes-dans-le-sud-du-pays_6691823_3210.html",
          "imageUrl": null,
          "source": "Le Monde - International",
          "category": "geopolitique",
          "publishedAt": "2026-05-28T00:45:56.000Z",
          "fetchedAt": "2026-05-28T05:02:58.764Z"
        },
        {
          "id": "2026-05-27-f087cd13",
          "title": "Jill Biden a pensé que Joe Biden était victime d’un AVC lors du débat présidentiel calamiteux avec Donald Trump en 2024",
          "description": "L’ancienne première dame des Etats-Unis a confié dans une interview avoir été « effrayée » en regardant la confrontation télévisée entre le candidat démocrate à la Maison Blanche et le milliardaire républicain. Elle assure n’avoir « jamais vu » son mari « comme ça avant ni depuis ».",
          "url": "https://www.lemonde.fr/international/article/2026/05/28/jill-biden-a-pense-que-joe-biden-faisait-un-avc-lors-du-debat-presidentiel-calamiteux-face-a-donald-trump-en-2024_6694270_3210.html",
          "imageUrl": null,
          "source": "Le Monde - International",
          "category": "geopolitique",
          "publishedAt": "2026-05-27T23:31:08.000Z",
          "fetchedAt": "2026-05-28T05:02:58.764Z"
        }
      ]
    },
    {
      "id": "cluster-11",
      "topic": "Stéphane Séjourné redoute « le retour aux nations » si les Européens n’engagent ",
      "category": "geopolitique",
      "importance": 10,
      "articles": [
        {
          "id": "2026-05-28-2e35485e",
          "title": "Stéphane Séjourné redoute « le retour aux nations » si les Européens n’engagent pas un « bras de fer » commercial avec la Chine",
          "description": "Le vice-président exécutif de la Commission s’alarme de la concurrence agressive de Pékin et appelle les Européens à muscler leurs instruments de défense.",
          "url": "https://www.lemonde.fr/economie/article/2026/05/28/stephane-sejourne-prevoit-le-retour-aux-nations-si-les-europeens-n-engagent-pas-un-bras-de-fer-commercial-avec-la-chine_6694419_3234.html",
          "imageUrl": null,
          "source": "Le Monde - International",
          "category": "geopolitique",
          "publishedAt": "2026-05-28T04:00:19.000Z",
          "fetchedAt": "2026-05-28T05:02:58.764Z"
        },
        {
          "id": "2026-05-28-a866735f",
          "title": "Sénégal: les milieux économiques attendent avec impatience la nomination d'un nouveau gouvernement",
          "description": "Au Sénégal, la crise politique au sommet de l’État a des répercussions financières. Le limogeage du Premier ministre Ousmane Sonko et l’absence d’un gouvernement ravivent la crainte des banques d’investissement d’un risque accru de défaut de paiement de sa dette extérieure. Un contexte qui met sous pression Bassirou Diomaye Faye alors que les consultations se poursuivent, depuis la nomination d'Ahmadou Ahminou Lo lundi, pour former rapidement un nouveau gouvernement.",
          "url": "https://www.rfi.fr/fr/afrique/20260528-s%C3%A9n%C3%A9gal-les-milieux-%C3%A9conomiques-attendent-avec-impatience-la-nomination-d-un-nouveau-gouvernement",
          "imageUrl": "https://s.rfi.fr/media/display/84a11458-587c-11f1-bd31-005056a97e36/w:1024/p:16x9/SENEGAL-RTS-Ahmadou-Al-Aminou-Mohamed-Lo.jpg",
          "source": "RFI",
          "category": "geopolitique",
          "publishedAt": "2026-05-28T03:57:54.000Z",
          "fetchedAt": "2026-05-28T05:03:08.707Z"
        },
        {
          "id": "2026-05-28-57ccfa03",
          "title": "Burkina Faso: une association étudiante suspendue, certains de ses membres interpellés",
          "description": "Au Burkina Faso, l'Union générale des étudiants du Burkina (Ugeb), la plus importante association d'étudiants du pays, a été suspendue pour trois mois, et des leaders, dont le nombre n'a pas été communiqué, ont été interpellés et conduits vers une destination inconnue. En cause: une déclaration du 19 mai, dans laquelle l'association dénonçait le manque de résultats dans le pays sur le plan de la lutte contre le terrorisme, malgré l'acquisition d'importants équipements militaires. Des déclarations qui n'ont pas été du goût des autorités, qui n'ont pas tardé à le faire savoir.",
          "url": "https://www.rfi.fr/fr/afrique/20260528-burkina-faso-une-association-%C3%A9tudiante-suspendue-certains-de-ses-membres-interpell%C3%A9s",
          "imageUrl": "https://s.rfi.fr/media/display/1bec048c-28e4-11ef-b6d4-005056bfb2b6/w:1024/p:16x9/000_34UG9ZN.jpg",
          "source": "RFI",
          "category": "geopolitique",
          "publishedAt": "2026-05-28T03:14:56.000Z",
          "fetchedAt": "2026-05-28T05:03:08.707Z"
        },
        {
          "id": "2026-05-28-8ee02648",
          "title": "Quand Pékin impose la sobriété à ses fonctionnaires, c’est le monde du vin qui trinque",
          "description": "En interdisant la consommation d’alcool lors des événements officiels, le président Xi Jinping a tari l’un des principaux marchés d’exportation pour les viticulteurs du monde entier. L’Australie et le Bordelais sont les régions productrices les plus durement touchées, selon “The Wall Street Journal”.",
          "url": "https://www.courrierinternational.com/article/alcool-quand-pekin-impose-la-sobriete-a-ses-fonctionnaires-c-est-le-monde-du-vin-qui-trinque_242272",
          "imageUrl": "https://focus.courrierinternational.com/2026/05/06/317/0/2126/1417/1200/630/60/0/d145b2c_upload-1-1pjfyps3ilmk-1falco-2013-12-12-0956-2-copie.jpg",
          "source": "Courrier International",
          "category": "geopolitique",
          "publishedAt": "2026-05-28T03:00:17.000Z",
          "fetchedAt": "2026-05-28T05:02:59.283Z"
        },
        {
          "id": "2026-05-27-317b5e2e",
          "title": "La présence de la ministre Annie Genevard au déjeuner du think tank de Vincent Bolloré fait polémique",
          "description": "Que faisait la ministre de l’Agriculture à un déjeuner organisé par le think tank créé par Vincent Bolloré, l’Institut de l’Espérance ? Annie Genevard se retrouve au cœur d’une polémique après la révélation de sa participation à cette réunion autour de personnalités conservatrices, proches de la droite radicale et de la sphère médiatique bolloréenne, dans le cadre d’un projet de cercle d’influence politique en vue de l’élection présidentielle de 2027. La polémique enfle.",
          "url": "https://www.rfi.fr/fr/france/20260527-la-pr%C3%A9sence-de-la-ministre-annie-genevard-au-d%C3%A9jeuner-du-think-tank-de-vincent-bollor%C3%A9-fait-pol%C3%A9mique",
          "imageUrl": "https://s.rfi.fr/media/display/44fb44ba-5a14-11f1-bd68-005056bfb2b6/w:1024/p:16x9/000-B3FD8RC.jpg",
          "source": "RFI",
          "category": "geopolitique",
          "publishedAt": "2026-05-27T22:07:46.000Z",
          "fetchedAt": "2026-05-28T05:03:08.707Z"
        },
        {
          "id": "2026-05-27-bc91a571",
          "title": "\"Parti des cafards\" : quand une blague devient un mouvement politique viral",
          "description": "Le \"Parti populaire des cafards\"... vous connaissez ? Né d'une blague en ligne après les propos polémiques d'un magistrat de la Cour Suprême en Inde relatifs à la jeunesse indienne, ce mouvement a très vite donné naissance à des revendications politiques concrètes jusqu'à inquiéter le gouvernement de Narendra Modi.",
          "url": "https://www.france24.com/fr/%C3%A9missions/info-ou-intox/20260527-parti-des-cafards-quand-une-blague-devient-un-mouvement-politique-viral",
          "imageUrl": "https://s.france24.com/media/display/174f792c-59f2-11f1-9841-005056bf30b7/w:1024/p:16x9/FRAN260526-2115-Live-CS2115.jpg",
          "source": "France 24",
          "category": "geopolitique",
          "publishedAt": "2026-05-27T19:03:52.000Z",
          "fetchedAt": "2026-05-28T05:02:58.810Z"
        }
      ]
    },
    {
      "id": "cluster-37",
      "topic": "La Norvège rejoint la « dissuasion nucléaire avancée » proposée par la France",
      "category": "geopolitique",
      "importance": 10,
      "articles": [
        {
          "id": "2026-05-27-10ad21e3",
          "title": "La Norvège rejoint la « dissuasion nucléaire avancée » proposée par la France",
          "description": "Huit pays avaient été d’emblée associés à la nouvelle doctrine dévoilée en mars par Emmanuel Macron dans un discours à l’île Longue : le Royaume-Uni, l’Allemagne, la Pologne, les Pays-Bas, la Belgique, la Grèce, la Suède et le Danemark.",
          "url": "https://www.lemonde.fr/international/article/2026/05/28/la-norvege-rejoint-la-dissuasion-nucleaire-avancee-proposee-par-la-france_6694268_3210.html",
          "imageUrl": null,
          "source": "Le Monde - International",
          "category": "geopolitique",
          "publishedAt": "2026-05-27T22:47:25.000Z",
          "fetchedAt": "2026-05-28T05:02:58.764Z"
        },
        {
          "id": "2026-05-27-a17b0205",
          "title": "La France annonce l'entrée de la Norvège dans son projet de \"dissuasion nucléaire avancée\"",
          "description": "Le président français Emmanuel Macron a annoncé mercredi que la Norvège a rejoint la \"dissuasion nucléaire avancée\" instaurée par la France. À ses côtés, le Premier ministre norvégien Jonas Gahr StøreLa a confirmé qu'Oslo souhaite y participer pour \"contribuer à la sécurité et à la dissuasion européennes contre les menaces militaires\".",
          "url": "https://www.france24.com/fr/europe/20260527-la-france-annonce-entr%C3%A9e-de-la-norv%C3%A8ge-dans-son-projet-de-dissuasion-nucl%C3%A9aire-avanc%C3%A9e",
          "imageUrl": "https://s.france24.com/media/display/380124a8-5a07-11f1-a2ef-005056bf30b7/w:1024/p:16x9/2026-05-27T184728Z-1285196072-RC2UHLAGOYCD-RTRMADP-3-FRANCE-NORWAY.jpg",
          "source": "France 24",
          "category": "geopolitique",
          "publishedAt": "2026-05-27T20:34:59.000Z",
          "fetchedAt": "2026-05-28T05:02:58.810Z"
        }
      ]
    },
    {
      "id": "cluster-1",
      "topic": "Meta lance des formules payantes d’abonnement pour Instagram, Facebook et WhatsA",
      "category": "tech",
      "importance": 7,
      "articles": [
        {
          "id": "2026-05-28-386dbde9",
          "title": "Meta lance des formules payantes d’abonnement pour Instagram, Facebook et WhatsApp",
          "description": "Il faudra débourser 3,99 dollars (soit 3,43 euros) par mois pour accéder à Instagram Plus et Facebook Plus et 2,99 dollars (soit 2,57 euros) par mois pour WhatsApp Plus, qui proposeront des fonctionnalités supplémentaires.",
          "url": "https://www.lemonde.fr/pixels/article/2026/05/28/meta-lance-des-formules-payantes-d-abonnement-pour-instagram-facebook-et-whatsapp_6694274_4408996.html",
          "imageUrl": null,
          "source": "Le Monde - Pixels",
          "category": "tech",
          "publishedAt": "2026-05-28T01:24:49.000Z",
          "fetchedAt": "2026-05-28T05:03:08.688Z"
        }
      ]
    },
    {
      "id": "cluster-5",
      "topic": "Why Fifa is being investigated over World Cup ticket prices",
      "category": "eco",
      "importance": 7,
      "articles": [
        {
          "id": "2026-05-28-786c2444",
          "title": "Why Fifa is being investigated over World Cup ticket prices",
          "description": "New York and New Jersey are looking into the association after fans have reportedly been \"misled\" over ticket sales and seat locations.",
          "url": "https://www.bbc.com/news/videos/cx2164ldp0ko?at_medium=RSS&at_campaign=rss",
          "imageUrl": "https://ichef.bbci.co.uk/news/1024/branded_news/7c5a/live/1bc4f3c0-5a28-11f1-89a3-d1f559421220.jpg",
          "source": "BBC Business",
          "category": "eco",
          "publishedAt": "2026-05-28T00:14:24.000Z",
          "fetchedAt": "2026-05-28T05:03:20.061Z"
        }
      ]
    }
  ]
}